{
  "matches": [
    {
      "match_id": 19389138,
      "date": "2025-10-21",
      "time": "22:00",
      "week": 3,
      "stadium": "Emirates",
      "importance_score": 8.0,
      "home_team": {
        "name": "Arsenal",
        "logo": "https://raw.githubusercontent.com/providedtroubleshoot/match.json/main/team_logos/logo_arsenal.png",
        "colors": ["#000000", "#FFFFFF"]
      },
      "away_team": {
        "name": "Atletico Madrid",
        "logo": "https://raw.githubusercontent.com/providedtroubleshoot/match.json/main/team_logos/logo_atm.png",
        "colors": ["#000000", "#FFFFFF"]
      }
    },
    {
      "match_id": 111293936,
      "date": "2025-10-21",
      "time": "22:00",
      "week": 3,
      "stadium": "BayArena",
      "importance_score": 6.0,
      "home_team": {
        "name": "Leverkusen",
        "logo": "https://raw.githubusercontent.com/providedtroubleshoot/match.json/main/team_logos/logo_b04.png",
        "colors": ["#006437", "#FFFFFF"]
      },
      "away_team": {
        "name": "PSG",
        "logo": "https://raw.githubusercontent.com/providedtroubleshoot/match.json/main/team_logos/logo_psg.png",
        "colors": ["#0033A0", "#FFFFFF"]
      }
    },
    {
      "match_id": 111293935,
      "date": "2025-10-21",
      "time": "22:00",
      "week": 3,
      "stadium": "BayArena",
      "importance_score": 6.0,
      "home_team": {
        "name": "Villarreal",
        "logo": "https://raw.githubusercontent.com/providedtroubleshoot/match.json/main/team_logos/logo_villarreal.png",
        "colors": ["#006437", "#FFFFFF"]
      },
      "away_team": {
        "name": "Man City",
        "logo": "https://raw.githubusercontent.com/providedtroubleshoot/match.json/main/team_logos/logo_mancity.png",
        "colors": ["#0033A0", "#FFFFFF"]
      }
    },
    {
      "match_id": 111293935,
      "date": "2025-10-22",
      "time": "22:00",
      "week": 3,
      "stadium": "BayArena",
      "importance_score": 6.0,
      "home_team": {
        "name": "Frankfurt",
        "logo": "https://raw.githubusercontent.com/providedtroubleshoot/match.json/main/team_logos/logo_frankfurt.png",
        "colors": ["#006437", "#FFFFFF"]
      },
      "away_team": {
        "name": "Liverpool",
        "logo": "https://raw.githubusercontent.com/providedtroubleshoot/match.json/main/team_logos/logo_liv.png",
        "colors": ["#0033A0", "#FFFFFF"]
      }
    },
    {
      "match_id": 111293935,
      "date": "2025-10-22",
      "time": "22:00",
      "week": 3,
      "stadium": "BayArena",
      "importance_score": 6.0,
      "home_team": {
        "name": "Monaco",
        "logo": "https://raw.githubusercontent.com/providedtroubleshoot/match.json/main/team_logos/logo_mco.png",
        "colors": ["#006437", "#FFFFFF"]
      },
      "away_team": {
        "name": "Tottenham",
        "logo": "https://raw.githubusercontent.com/providedtroubleshoot/match.json/main/team_logos/logo_tottenham.png",
        "colors": ["#0033A0", "#FFFFFF"]
      }
    },
    {
      "match_id": 111293935,
      "date": "2025-10-22",
      "time": "22:00",
      "week": 3,
      "stadium": "BayArena",
      "importance_score": 6.0,
      "home_team": {
        "name": "Real Madrid",
        "logo": "https://raw.githubusercontent.com/providedtroubleshoot/match.json/main/team_logos/logo_rma.png",
        "colors": ["#006437", "#FFFFFF"]
      },
      "away_team": {
        "name": "Juventus",
        "logo": "https://raw.githubusercontent.com/providedtroubleshoot/match.json/main/team_logos/logo_juventus.png",
        "colors": ["#0033A0", "#FFFFFF"]
      }
    }
  ]
}
