{
  "matches": [
    {
      "match_id": 2500,
      "date": "2025-08-22",
      "time": "22:00",
      "week": 2,
      "stadium": "London Stadium",
      "importance_score": 7.2,
      "home_team": {
        "name": "West Ham",
        "logo": "https://raw.githubusercontent.com/providedtroubleshoot/match.json/main/team_logos/logo_westh.png",
        "colors": ["#7A263A", "#1BB1E7"]
      },
      "away_team": {
        "name": "Chelsea",
        "logo": "https://raw.githubusercontent.com/providedtroubleshoot/match.json/main/team_logos/logo_chelsea.png",
        "colors": ["#034694", "#FFFFFF"]
      }
    },
    {
      "match_id": 2501,
      "date": "2025-08-23",
      "time": "14:30",
      "week": 2,
      "stadium": "Etihad Stadium",
      "importance_score": 9.0,
      "home_team": {
        "name": "Man City",
        "logo": "https://raw.githubusercontent.com/providedtroubleshoot/match.json/main/team_logos/logo_mancity.png",
        "colors": ["#6CABDD", "#FFFFFF"]
      },
      "away_team": {
        "name": "Tottenham",
        "logo": "https://raw.githubusercontent.com/providedtroubleshoot/match.json/main/team_logos/logo_tottenham.png",
        "colors": ["#132257", "#FFFFFF"]
      }
    },
    {
      "match_id": 2502,
      "date": "2025-08-23",
      "time": "17:00",
      "week": 2,
      "stadium": "Vitality Stadium",
      "importance_score": 5.5,
      "home_team": {
        "name": "Bournemouth",
        "logo": "https://raw.githubusercontent.com/providedtroubleshoot/match.json/main/team_logos/logo_bour.png",
        "colors": ["#DA291C", "#000000"]
      },
      "away_team": {
        "name": "Wolves",
        "logo": "https://raw.githubusercontent.com/providedtroubleshoot/match.json/main/team_logos/logo_wolves.png",
        "colors": ["#FDB913", "#231F20"]
      }
    },
    {
      "match_id": 2503,
      "date": "2025-08-23",
      "time": "17:00",
      "week": 2,
      "stadium": "Gtech Community Stadium",
      "importance_score": 6.0,
      "home_team": {
        "name": "Brentford",
        "logo": "https://raw.githubusercontent.com/providedtroubleshoot/match.json/main/team_logos/logo_brentford.png",
        "colors": ["#FF0000", "#FFFFFF"]
      },
      "away_team": {
        "name": "Aston Villa",
        "logo": "https://raw.githubusercontent.com/providedtroubleshoot/match.json/main/team_logos/logo_asvilla.png",
        "colors": ["#95BFE5", "#670E36"]
      }
    },
    {
      "match_id": 2504,
      "date": "2025-08-23",
      "time": "17:00",
      "week": 2,
      "stadium": "Turf Moor",
      "importance_score": 4.3,
      "home_team": {
        "name": "Burnley",
        "logo": "https://raw.githubusercontent.com/providedtroubleshoot/match.json/main/team_logos/logo_burnley.png",
        "colors": ["#6C1D45", "#99D6EA"]
      },
      "away_team": {
        "name": "Sunderland",
        "logo": "https://raw.githubusercontent.com/providedtroubleshoot/match.json/main/team_logos/logo_sunderland.png",
        "colors": ["#D71920", "#FFFFFF"]
      }
    },
    {
      "match_id": 2505,
      "date": "2025-08-23",
      "time": "19:30",
      "week": 2,
      "stadium": "Emirates Stadium",
      "importance_score": 8.8,
      "home_team": {
        "name": "Arsenal",
        "logo": "https://raw.githubusercontent.com/providedtroubleshoot/match.json/main/team_logos/logo_arsenal.png",
        "colors": ["#EF0107", "#FFFFFF"]
      },
      "away_team": {
        "name": "Leeds",
        "logo": "https://raw.githubusercontent.com/providedtroubleshoot/match.json/main/team_logos/logo_leeds.png",
        "colors": ["#FFCD00", "#1D428A"]
      }
    },
    {
      "match_id": 2506,
      "date": "2025-08-24",
      "time": "16:00",
      "week": 2,
      "stadium": "Selhurst Park",
      "importance_score": 5.8,
      "home_team": {
        "name": "Crystal Palace",
        "logo": "https://raw.githubusercontent.com/providedtroubleshoot/match.json/main/team_logos/logo_cry.png",
        "colors": ["#1B458F", "#A7A5A6"]
      },
      "away_team": {
        "name": "Nottingham",
        "logo": "https://raw.githubusercontent.com/providedtroubleshoot/match.json/main/team_logos/logo_notting.png",
        "colors": ["#DD0000", "#FFFFFF"]
      }
    },
    {
      "match_id": 2507,
      "date": "2025-08-24",
      "time": "16:00",
      "week": 2,
      "stadium": "Goodison Park",
      "importance_score": 6.0,
      "home_team": {
        "name": "Everton",
        "logo": "https://raw.githubusercontent.com/providedtroubleshoot/match.json/main/team_logos/logo_everton.png",
        "colors": ["#003399", "#FFFFFF"]
      },
      "away_team": {
        "name": "Brighton",
        "logo": "https://raw.githubusercontent.com/providedtroubleshoot/match.json/main/team_logos/logo_brighton.png",
        "colors": ["#0057B8", "#FFFFFF"]
      }
    },
    {
      "match_id": 2508,
      "date": "2025-08-24",
      "time": "18:30",
      "week": 2,
      "stadium": "Craven Cottage",
      "importance_score": 8.5,
      "home_team": {
        "name": "Fulham",
        "logo": "https://raw.githubusercontent.com/providedtroubleshoot/match.json/main/team_logos/logo_fulham.png",
        "colors": ["#000000", "#FFFFFF"]
      },
      "away_team": {
        "name": "Man United",
        "logo": "https://raw.githubusercontent.com/providedtroubleshoot/match.json/main/team_logos/logo_manutd.png",
        "colors": ["#DA291C", "#FBE122"]
      }
    },
    {
      "match_id": 2509,
      "date": "2025-08-25",
      "time": "22:00",
      "week": 2,
      "stadium": "St. James' Park",
      "importance_score": 9.1,
      "home_team": {
        "name": "Newcastle",
        "logo": "https://raw.githubusercontent.com/providedtroubleshoot/match.json/main/team_logos/logo_newc.png",
        "colors": ["#241F20", "#FFFFFF"]
      },
      "away_team": {
        "name": "Liverpool",
        "logo": "https://raw.githubusercontent.com/providedtroubleshoot/match.json/main/team_logos/logo_liv.png",
        "colors": ["#C8102E", "#FFFFFF"]
      }
    }
  ]
}